torch_runstats/__init__.py
torch_runstats/_runstats.py
torch_runstats/_version.py
torch_runstats/scatter.py
torch_runstats-0.2.0.dist-info/LICENSE
torch_runstats-0.2.0.dist-info/METADATA
torch_runstats-0.2.0.dist-info/WHEEL
torch_runstats-0.2.0.dist-info/top_level.txt
torch_runstats-0.2.0.dist-info/RECORD
