Metadata-Version: 2.1
Name: torch-runstats
Version: 0.2.0
Summary: Running/online statistics for PyTorch 
Home-page: https://github.com/mir-group/pytorch_runstats
License: MIT
Project-URL: Bug Tracker, https://github.com/mir-group/pytorch_runstats/issues
Platform: UNKNOWN
Classifier: Programming Language :: Python :: 3
Classifier: License :: OSI Approved :: MIT License
Classifier: Operating System :: OS Independent
Classifier: Development Status :: 4 - Beta
Requires-Python: >=3.6
